discordhealthcheck/__init__.py
discordhealthcheck/__main__.py
discordhealthcheck/core.py
discordhealthcheck-0.1.1.dist-info/LICENSE
discordhealthcheck-0.1.1.dist-info/METADATA
discordhealthcheck-0.1.1.dist-info/WHEEL
discordhealthcheck-0.1.1.dist-info/entry_points.txt
discordhealthcheck-0.1.1.dist-info/top_level.txt
discordhealthcheck-0.1.1.dist-info/RECORD
