Metadata-Version: 2.1
Name: discordhealthcheck
Version: 0.1.1
Summary: A small Python 3 library and command line app to automate Docker health checks for discord.py bots.
Home-page: https://github.com/psidex/discordhealthcheck
Keywords: discord discord.py docker healthcheck health check bot
Classifier: Intended Audience :: Developers
Classifier: License :: OSI Approved :: MIT License
Classifier: Programming Language :: Python :: 3
License-File: LICENSE
Requires-Dist: discord.py
